patch_package.py
patch_package-0.1.3.dist-info/LICENSE
patch_package-0.1.3.dist-info/METADATA
patch_package-0.1.3.dist-info/WHEEL
patch_package-0.1.3.dist-info/entry_points.txt
patch_package-0.1.3.dist-info/RECORD
